devdocs_crawler/cli.py
devdocs_crawler/crawler.py
devdocs_crawler/utils.py
devdocs_crawler-0.1.0.dist-info/licenses/LICENSE
devdocs_crawler-0.1.0.dist-info/METADATA
devdocs_crawler-0.1.0.dist-info/WHEEL
devdocs_crawler-0.1.0.dist-info/entry_points.txt
devdocs_crawler-0.1.0.dist-info/top_level.txt
devdocs_crawler-0.1.0.dist-info/RECORD
