Metadata-Version: 2.4
Name: devdocs-crawler
Version: 0.1.0
Summary: A CLI tool to crawl developer documentation sites and save pages as Markdown using crawl4ai.
Author-email: Youssef Tharwat <yousseftharwat.khalil@tharwat.com>
License-Expression: MIT
Project-URL: Homepage, https://github.com/youssef-tharwat/devdocs-crawler
Project-URL: Bug Tracker, https://github.com/youssef-tharwat/devdocs-crawler/issues
Classifier: Programming Language :: Python :: 3
Classifier: Programming Language :: Python :: 3.9
Classifier: Programming Language :: Python :: 3.10
Classifier: Programming Language :: Python :: 3.11
Classifier: Programming Language :: Python :: 3.12
Classifier: Operating System :: OS Independent
Classifier: Topic :: Documentation
Classifier: Topic :: Internet :: WWW/HTTP :: Indexing/Search
Classifier: Topic :: Software Development :: Documentation
Classifier: Topic :: Utilities
Classifier: Environment :: Console
Classifier: Intended Audience :: Developers
Requires-Python: >=3.12
License-File: LICENSE
Requires-Dist: crawl4ai<0.6.0,>=0.5.0
Requires-Dist: click<9.0,>=8.0
Requires-Dist: aiofiles>=24.1.0
Requires-Dist: pathvalidate>=3.2.3
Provides-Extra: dev
Requires-Dist: ruff>=0.1; extra == "dev"
Requires-Dist: uv>=0.1; extra == "dev"
Dynamic: license-file
